odoo10_addon_account_payment_residual_amount-10.0.1.0.0.99.dev4-py3.8-nspkg.pth
odoo/addons/account_payment_residual_amount/README.rst
odoo/addons/account_payment_residual_amount/__init__.py
odoo/addons/account_payment_residual_amount/__manifest__.py
odoo/addons/account_payment_residual_amount/i18n/account_payment_residual_amount.pot
odoo/addons/account_payment_residual_amount/models/__init__.py
odoo/addons/account_payment_residual_amount/models/account_payment.py
odoo/addons/account_payment_residual_amount/readme/CONTRIBUTORS.rst
odoo/addons/account_payment_residual_amount/readme/DESCRIPTION.rst
odoo/addons/account_payment_residual_amount/static/description/icon.png
odoo/addons/account_payment_residual_amount/static/description/index.html
odoo/addons/account_payment_residual_amount/static/description/payments_view.png
odoo/addons/account_payment_residual_amount/tests/__init__.py
odoo/addons/account_payment_residual_amount/tests/test_account_payment_residual_amount.py
odoo/addons/account_payment_residual_amount/views/account_payment_view.xml
odoo10_addon_account_payment_residual_amount-10.0.1.0.0.99.dev4.dist-info/METADATA
odoo10_addon_account_payment_residual_amount-10.0.1.0.0.99.dev4.dist-info/WHEEL
odoo10_addon_account_payment_residual_amount-10.0.1.0.0.99.dev4.dist-info/namespace_packages.txt
odoo10_addon_account_payment_residual_amount-10.0.1.0.0.99.dev4.dist-info/top_level.txt
odoo10_addon_account_payment_residual_amount-10.0.1.0.0.99.dev4.dist-info/RECORD
